mandelbrot/__init__.py
mandelbrot/__main__.py
mandelbrot/mandelbrot_set.py
mandelbrot/plot.py
mandelbrot/viewport.py
lf_mandelbrot-0.1.0.dist-info/LICENSE
lf_mandelbrot-0.1.0.dist-info/METADATA
lf_mandelbrot-0.1.0.dist-info/WHEEL
lf_mandelbrot-0.1.0.dist-info/entry_points.txt
lf_mandelbrot-0.1.0.dist-info/top_level.txt
lf_mandelbrot-0.1.0.dist-info/RECORD
