Metadata-Version: 2.1
Name: lf-mandelbrot
Version: 0.1.0
Summary: Paint the Mandelbrot set.
Author-email: Real Python <info@realpython.com>
License: This is free and unencumbered software released into the public domain.
Project-URL: Homepage, https://github.com/lfavole/mandelbrot
Keywords: mandelbrot
Classifier: License :: OSI Approved :: MIT License
Classifier: Programming Language :: Python
Classifier: Programming Language :: Python :: 3
Requires-Python: >=3.7
License-File: LICENSE
Requires-Dist: matplotlib
Requires-Dist: numpy
Requires-Dist: Pillow
Provides-Extra: build
Requires-Dist: build ; extra == 'build'
Requires-Dist: twine ; extra == 'build'
Provides-Extra: dev
Requires-Dist: black ; extra == 'dev'
Requires-Dist: bumpver ; extra == 'dev'
Requires-Dist: isort ; extra == 'dev'
Requires-Dist: pip-tools ; extra == 'dev'
Requires-Dist: pytest ; extra == 'dev'
